Metadata-Version: 2.1
Name: oneNeuron-pypi-jrk90210us
Version: 0.0.3
Summary: Packaging Perceptron - oneNeuron
Home-page: https://github.com/jrk90210us/oneNeuron_pypi
Author: Jatin
Author-email: jrk90210us@gmail.com
License: UNKNOWN
Project-URL: Bug Tracker, https://github.com/jrk90210us/oneNeuron_pypi/issues
Platform: UNKNOWN
Classifier: Programming Language :: Python :: 3
Classifier: License :: OSI Approved :: MIT License
Classifier: Operating System :: OS Independent
Requires-Python: >=3.7
License-File: LICENSE
Requires-Dist: numpy
Requires-Dist: tqdm
Requires-Dist: matplotlib
Requires-Dist: pandas
Requires-Dist: joblib
